parent_class/ParentClass.py
parent_class/ParentPlural.py
parent_class/ParentPluralDict.py
parent_class/ParentPluralList.py
parent_class/__init__.py
parent_class/__main__.py
kabbes_parent_class-0.7.0.dist-info/LICENSE
kabbes_parent_class-0.7.0.dist-info/METADATA
kabbes_parent_class-0.7.0.dist-info/WHEEL
kabbes_parent_class-0.7.0.dist-info/top_level.txt
kabbes_parent_class-0.7.0.dist-info/RECORD
