Metadata-Version: 2.1
Name: kabbes-parent-class
Version: 0.7.0
Summary: Parent Class for generic Python use
Home-page: https://pypi.org/project/kabbes-parent-class/
Author: James Kabbes
Author-email: james.kabbes@gmail.com
Project-URL: GitHub, https://github.com/jameskabbes/parent_class
Project-URL: Documentation, https://jameskabbes.github.io/parent_class
Classifier: Programming Language :: Python :: 3
Classifier: License :: OSI Approved :: MIT License
Classifier: Operating System :: OS Independent
Requires-Python: >=3.7
License-File: LICENSE
Requires-Dist: kabbes-py-starter
